[
    {
    "id": 1,
    "statement": "Python is a statically typed language.",
    "options": ["True", "False"],
    "answer": "False"
  },
  {
    "id": 2,
    "statement": "C++ supports operator overloading.",
    "options": ["True", "False"],
    "answer": "True"
  },
  {
    "id": 3,
    "statement": "A destructor in C++ can be overloaded.",
    "options": ["True", "False"],
    "answer": "False"
  },
  {
    "id": 4,
    "statement": "OSI model has 7 layers.",
    "options": ["True", "False"],
    "answer": "True"
  },
  {
    "id": 5,
    "statement": "TCP/IP model has 5 layers.",
    "options": ["True", "False"],
    "answer": "True"
  },
  {
    "id": 6,
    "statement": "Machine language is the lowest-level programming language.",
    "options": ["True", "False"],
    "answer": "True"
  },
  {
    "id": 7,
    "statement": "Assembly language uses mnemonics for instructions.",
    "options": ["True", "False"],
    "answer": "True"
  },
  {
    "id": 8,
    "statement": "In C, switch-case can handle float values.",
    "options": ["True", "False"],
    "answer": "False"
  },
  {
    "id": 9,
    "statement": "In OOP, an abstract class can be instantiated directly.",
    "options": ["True", "False"],
    "answer": "False"
  },
  {
    "id": 10,
    "statement": "Recursion always uses a stack for execution.",
    "options": ["True", "False"],
    "answer": "True"
  }
]